seabreeze/__init__.py
seabreeze/_cli.py
seabreeze/_exc.py
seabreeze/_version.py
seabreeze/backends.py
seabreeze/os_setup.py
seabreeze/py.typed
seabreeze/spectrometers.py
seabreeze/types.py
seabreeze/cseabreeze/__init__.py
seabreeze/cseabreeze/_wrapper.cp311-win32.pyd
seabreeze/pyseabreeze/__init__.py
seabreeze/pyseabreeze/api.py
seabreeze/pyseabreeze/config.py
seabreeze/pyseabreeze/devices.py
seabreeze/pyseabreeze/exceptions.py
seabreeze/pyseabreeze/protocol.py
seabreeze/pyseabreeze/transport.py
seabreeze/pyseabreeze/types.py
seabreeze/pyseabreeze/features/__init__.py
seabreeze/pyseabreeze/features/_base.py
seabreeze/pyseabreeze/features/acquisitiondelay.py
seabreeze/pyseabreeze/features/continuousstrobe.py
seabreeze/pyseabreeze/features/databuffer.py
seabreeze/pyseabreeze/features/dhcpserver.py
seabreeze/pyseabreeze/features/eeprom.py
seabreeze/pyseabreeze/features/ethernetconfiguration.py
seabreeze/pyseabreeze/features/fastbuffer.py
seabreeze/pyseabreeze/features/fpga.py
seabreeze/pyseabreeze/features/gpio.py
seabreeze/pyseabreeze/features/i2cmaster.py
seabreeze/pyseabreeze/features/introspection.py
seabreeze/pyseabreeze/features/ipv4.py
seabreeze/pyseabreeze/features/irradcal.py
seabreeze/pyseabreeze/features/lightsource.py
seabreeze/pyseabreeze/features/multicast.py
seabreeze/pyseabreeze/features/networkconfiguration.py
seabreeze/pyseabreeze/features/nonlinearity.py
seabreeze/pyseabreeze/features/opticalbench.py
seabreeze/pyseabreeze/features/pixelbinning.py
seabreeze/pyseabreeze/features/rawusb.py
seabreeze/pyseabreeze/features/revision.py
seabreeze/pyseabreeze/features/shutter.py
seabreeze/pyseabreeze/features/spectrometer.py
seabreeze/pyseabreeze/features/spectrumprocessing.py
seabreeze/pyseabreeze/features/straylightcoefficients.py
seabreeze/pyseabreeze/features/strobelamp.py
seabreeze/pyseabreeze/features/temperature.py
seabreeze/pyseabreeze/features/thermoelectric.py
seabreeze/pyseabreeze/features/wificonfiguration.py
seabreeze-2.10.1.dist-info/LICENSE.md
seabreeze-2.10.1.dist-info/METADATA
seabreeze-2.10.1.dist-info/WHEEL
seabreeze-2.10.1.dist-info/entry_points.txt
seabreeze-2.10.1.dist-info/top_level.txt
seabreeze-2.10.1.dist-info/RECORD
