Metadata-Version: 2.2
Name: seabreeze
Version: 2.10.1
Summary: Python interface module for Ocean Optics spectrometers. This software is not associated with Ocean Optics. Use it at your own risk.
Home-page: https://github.com/ap--/python-seabreeze
Author: Andreas Poehlmann
Author-email: andreas@poehlmann.io
License: MIT
Classifier: Programming Language :: Python :: 3
Classifier: Programming Language :: Python :: 3.9
Classifier: Programming Language :: Python :: 3.10
Classifier: Programming Language :: Python :: 3.11
Classifier: Programming Language :: Python :: 3.12
Classifier: Programming Language :: Python :: 3.13
Requires-Python: >=3.9
License-File: LICENSE.md
Requires-Dist: numpy>=1.21
Provides-Extra: cseabreeze
Provides-Extra: pyseabreeze
Requires-Dist: pyusb>=1.0; extra == "pyseabreeze"
Provides-Extra: docs
Requires-Dist: sphinx; extra == "docs"
Requires-Dist: sphinx-rtd-theme; extra == "docs"
Provides-Extra: tests
Requires-Dist: pytest; python_version <= "3.9" and extra == "tests"
Requires-Dist: pytest>=6.2.4; python_version > "3.9" and extra == "tests"
Dynamic: author
Dynamic: author-email
Dynamic: classifier
Dynamic: description
Dynamic: description-content-type
Dynamic: home-page
Dynamic: license
Dynamic: provides-extra
Dynamic: requires-dist
Dynamic: requires-python
Dynamic: summary
